<?xml version="1.0" encoding="utf-8"?>
<openerp>
    <data>


        <act_window id="action_batch_approval_wizard"
                    multi="True"
                    key2="client_action_multi" name="批量操作BOM"
                    res_model="batch.approval.wizard" src_model="mrp.bom"
                    context="{'review_type':'bom_review'}"
                    view_mode="form" target="new" view_type="form"/>

        <record id="review_process_wizard_form" model="ir.ui.view">
            <field name="name">选择下一个审核人</field>
            <field name="model">batch.approval.wizard</field>
            <field name="arch" type="xml">
                <form string="选择下一个审核人">
                    <sheet>
                        <group>
                            <field name="cur_partner_id" invisible="1"/>
                            <field name="partner_id" require="1"
                                   domain="[('id','!=',cur_partner_id),('employee', '=', True)]" string="审核人"
                                   options="{'no_create':True}"/>
                            <field name="remark"/>
                        </group>
                    </sheet>
                    <footer>
                        <button name='action_to_next' type='object' string='送审' class='oe_highlight review_reload'/>

                        <button name='action_pass' type='object' string='审核通过' class='oe_highlight review_reload'
                                groups="linkloving_pdm.group_final_review_partner_bom"/>

                        <button string='取消' class='oe_link review_reload' special='cancel'/>
                    </footer>
                </form>
            </field>
        </record>
    </data>
</openerp>